winsvc/__init__.py
winsvc/_svc.py
winsvc/cmd.py
winsvc/svc.py
winsvc-1.0.0.dist-info/METADATA
winsvc-1.0.0.dist-info/WHEEL
winsvc-1.0.0.dist-info/top_level.txt
winsvc-1.0.0.dist-info/RECORD
