Metadata-Version: 2.1
Name: winsvc
Version: 1.0.0
Summary: Windows Service Creator
Home-page: https://github.com/koho/winsvc
Author: Gerhard Tan
Author-email: gerhard.gh.ta@gmail.com
License: UNKNOWN
Platform: any
Requires-Dist: click
Requires-Dist: pywin32 ; sys_platform == "win32"
